la_forge/__init__.py
la_forge/bfacs.py
la_forge/core.py
la_forge/diagnostics.py
la_forge/gp.py
la_forge/rednoise.py
la_forge/slices.py
la_forge/utils.py
la_forge-1.1.0.dist-info/AUTHORS.rst
la_forge-1.1.0.dist-info/LICENSE
la_forge-1.1.0.dist-info/METADATA
la_forge-1.1.0.dist-info/WHEEL
la_forge-1.1.0.dist-info/top_level.txt
la_forge-1.1.0.dist-info/RECORD
