Metadata-Version: 2.1
Name: la-forge
Version: 1.1.0
Summary: Python package for conveniently plotting results from pulsar timing array bayesian analyses. 
Home-page: https://github.com/Hazboun6/la_forge
Author: Jeffrey Shafiq Hazboun
Author-email: jeffrey.hazboun@gmail.com
License: MIT license
Keywords: la_forge
Classifier: Development Status :: 2 - Pre-Alpha
Classifier: Intended Audience :: Developers
Classifier: License :: OSI Approved :: MIT License
Classifier: Natural Language :: English
Classifier: Programming Language :: Python :: 3
Classifier: Programming Language :: Python :: 3.8
Classifier: Programming Language :: Python :: 3.9
Classifier: Programming Language :: Python :: 3.10
License-File: LICENSE
License-File: AUTHORS.rst
Requires-Dist: numpy >=1.16
Requires-Dist: scipy >=1.0.0
Requires-Dist: matplotlib >=2.0.0
Requires-Dist: corner
Requires-Dist: h5py >=3.4.0
Requires-Dist: astropy >=3.0
Requires-Dist: six
